{
  "dogs": [
    {
      "dogName": "Luca",
      "dogBreed": "German Shepherd",
      "id": 1
    },
    {
      "dogName": "Lola",
      "dogBreed": "Giant Schnauzer",
      "id": 2
    },
    {
      "dogName": "Byron",
      "dogBreed": "Poodle",
      "id": 3
    }
  ],
  "cats": [
    {
      "catName": "Stanley",
      "catBreed": "Tabby",
      "id": 1
      
    }
  ],
  "users": [
    {
      "name": "Jim",
      "email": "jim@jim.com",
      "id": 1
    },
    {
      "name": "Jim",
      "email": "jim@jim.com",
      "id": 2
    },
    {
      "name": "Sam",
      "email": "sam@sam.com",
      "id": 336
    },
    {
      "name": "Sam",
      "email": "sam@sam.com",
      "id": 4
    },
    {
      "name": "Steve",
      "email": "steve@steve.com",
      "id": 5
    },
    {
      "name": "Steve",
      "email": "steve@steve.com",
      "id": 6
    },
    {
      "name": "Steve",
      "email": "steve@steve.com",
      "id": 7
    },
    {
      "name": "Steve",
      "email": "steve@steve.com",
      "id": 8
    },
    {
      "name": "Steve",
      "email": "steve@steve.com",
      "id": 9
    },
    {
      "name": "Steve",
      "email": "steve@steve.com",
      "id": 10
    }
  ]}